LICENSE
MANIFEST.in
README.md
setup.py
bmd/__init__.py
bmd/bmd.py
bmd.egg-info/PKG-INFO
bmd.egg-info/SOURCES.txt
bmd.egg-info/dependency_links.txt
bmd.egg-info/entry_points.txt
bmd.egg-info/not-zip-safe
bmd.egg-info/requires.txt
bmd.egg-info/top_level.txt