Metadata-Version: 1.0
Name: bmd
Version: 0.0.1
Summary: Baidu 320k Music Downloader
Home-page: https://github.com/maralla/bmd
Author: Maralla
Author-email: maralla.ai@gmail.com
License: MIT
Platform: UNKNOWN
